{
  "getVisitorsFunction": {
    "APP_FRONTEND_BASE_URL": "http://localhost:8080",
    "ENDPOINT_OVERRIDE": "http://172.17.0.2:8000",
    "VISITORS_TABLE": "VisitorsTable"
  },
  "getPermissionsFunction": {
    "APP_FRONTEND_BASE_URL": "http://localhost:8080",
    "POLICY_STORE_ID": "<your-policy-store-id>"
  },
  "getVisitRequestsFunction": {
    "APP_FRONTEND_BASE_URL": "http://localhost:8080",
    "ENDPOINT_OVERRIDE": "http://172.17.0.2:8000",
    "VISIT_REQUESTS_TABLE": "VisitRequestsTable"
  },
  "getVisitorByIdFunction": {
    "APP_FRONTEND_BASE_URL": "http://localhost:8080",
    "ENDPOINT_OVERRIDE": "http://172.17.0.2:8000",
    "VISITORS_TABLE": "VisitorsTable"
  },
  "getInviteByTokenFunction": {
    "APP_FRONTEND_BASE_URL": "http://localhost:8080",
    "ENDPOINT_OVERRIDE": "http://172.17.0.2:8000",
    "INVITE_LINKS_TABLE": "InviteLinksTable"
  },
  "getVisitRequestByTokenFunction": {
    "APP_FRONTEND_BASE_URL": "http://localhost:8080",
    "ENDPOINT_OVERRIDE": "http://172.17.0.2:8000",
    "VISIT_REQUESTS_TABLE": "VisitRequestsTable"
  },
  "putVisitorFunction": {
    "APP_FRONTEND_BASE_URL": "http://localhost:8080",
    "ENDPOINT_OVERRIDE": "http://172.17.0.2:8000",
    "VISITORS_TABLE": "VisitorsTable"
  },
  "putInviteLinkFunction": {
    "APP_FRONTEND_BASE_URL": "http://localhost:8080",
    "ENDPOINT_OVERRIDE": "http://172.17.0.2:8000",
    "INVITE_LINKS_TABLE": "InviteLinksTable"
  },
  "putVisitRequestFunction": {
    "APP_FRONTEND_BASE_URL": "http://localhost:8080",
    "ENDPOINT_OVERRIDE": "http://172.17.0.2:8000",
    "VISIT_REQUESTS_TABLE": "VisitRequestsTable"
  }
}
